{"postId":1566297,"headline":"In my opinion using the same weapon is kinda boring, also fuse ability is a thing","publishedAt":"2023-05-27T09:51:54.026Z","shareOfPost":"https://cohost.org/kaara/post/1493317-hesitant-to-admit-i","state":1,"cws":["TotK spoiler but not really since it's already shown in the trailer"],"tags":[],"blocks":[{"type":"markdown","markdown":{"content":"https://youtu.be/oKdkUPe1a7o"}}],"pinned":false,"commentsLocked":false,"sharesLocked":false,"singlePostPageUrl":"https://cohost.org/lts20050703/post/1566297-in-my-opinion-using"}